<?xml version="1.0" encoding="utf-8" ?>
<dwsync>
<file name="ar.js" server="froala.safedronezone.com" local="131338806520000000" remote="131408062200000000" Dst="0" />
<file name="bs.js" server="froala.safedronezone.com" local="131338806520000000" remote="131408062200000000" Dst="0" />
<file name="cs.js" server="froala.safedronezone.com" local="131338806520000000" remote="131408062200000000" Dst="0" />
<file name="da.js" server="froala.safedronezone.com" local="131338806520000000" remote="131408062200000000" Dst="0" />
<file name="de.js" server="froala.safedronezone.com" local="131338806520000000" remote="131408062200000000" Dst="0" />
<file name="en_ca.js" server="froala.safedronezone.com" local="131338806520000000" remote="131408062200000000" Dst="0" />
<file name="en_gb.js" server="froala.safedronezone.com" local="131338806520000000" remote="131408062200000000" Dst="0" />
<file name="es.js" server="froala.safedronezone.com" local="131338806520000000" remote="131408062200000000" Dst="0" />
<file name="et.js" server="froala.safedronezone.com" local="131338806520000000" remote="131408062200000000" Dst="0" />
<file name="fa.js" server="froala.safedronezone.com" local="131338806520000000" remote="131408062200000000" Dst="0" />
<file name="fr.js" server="froala.safedronezone.com" local="131338806520000000" remote="131408062200000000" Dst="0" />
<file name="he.js" server="froala.safedronezone.com" local="131338806520000000" remote="131408062200000000" Dst="0" />
<file name="fi.js" server="froala.safedronezone.com" local="131338806520000000" remote="131408062200000000" Dst="0" />
<file name="hr.js" server="froala.safedronezone.com" local="131338806520000000" remote="131408062200000000" Dst="0" />
<file name="hu.js" server="froala.safedronezone.com" local="131338806520000000" remote="131408062200000000" Dst="0" />
<file name="id.js" server="froala.safedronezone.com" local="131338806520000000" remote="131408062200000000" Dst="0" />
<file name="ja.js" server="froala.safedronezone.com" local="131338806520000000" remote="131408062200000000" Dst="0" />
<file name="ko.js" server="froala.safedronezone.com" local="131338806520000000" remote="131408062200000000" Dst="0" />
<file name="it.js" server="froala.safedronezone.com" local="131338806520000000" remote="131408062200000000" Dst="0" />
<file name="me.js" server="froala.safedronezone.com" local="131338806520000000" remote="131408062200000000" Dst="0" />
<file name="nb.js" server="froala.safedronezone.com" local="131338806520000000" remote="131408062200000000" Dst="0" />
<file name="nl.js" server="froala.safedronezone.com" local="131338806520000000" remote="131408062200000000" Dst="0" />
<file name="pl.js" server="froala.safedronezone.com" local="131338806520000000" remote="131408062200000000" Dst="0" />
<file name="pt_br.js" server="froala.safedronezone.com" local="131338806520000000" remote="131408062200000000" Dst="0" />
<file name="pt_pt.js" server="froala.safedronezone.com" local="131338806520000000" remote="131408062200000000" Dst="0" />
<file name="ro.js" server="froala.safedronezone.com" local="131338806520000000" remote="131408062200000000" Dst="0" />
<file name="ru.js" server="froala.safedronezone.com" local="131338806520000000" remote="131408062200000000" Dst="0" />
<file name="sk.js" server="froala.safedronezone.com" local="131338806520000000" remote="131408062200000000" Dst="0" />
<file name="sr.js" server="froala.safedronezone.com" local="131338806520000000" remote="131408062200000000" Dst="0" />
<file name="tr.js" server="froala.safedronezone.com" local="131338806520000000" remote="131408062800000000" Dst="0" />
<file name="sv.js" server="froala.safedronezone.com" local="131338806520000000" remote="131408062800000000" Dst="0" />
<file name="th.js" server="froala.safedronezone.com" local="131338806520000000" remote="131408062800000000" Dst="0" />
<file name="vi.js" server="froala.safedronezone.com" local="131338806520000000" remote="131408062800000000" Dst="0" />
<file name="zh_cn.js" server="froala.safedronezone.com" local="131338806520000000" remote="131408062800000000" Dst="0" />
<file name="ua.js" server="froala.safedronezone.com" local="131338806520000000" remote="131408062800000000" Dst="0" />
<file name="zh_tw.js" server="froala.safedronezone.com" local="131338806520000000" remote="131408062800000000" Dst="0" />
<file name="ar.js" server="smoothgraph.co.th" local="131338806520000000" remote="131408089200000000" Dst="0" />
<file name="bs.js" server="smoothgraph.co.th" local="131338806520000000" remote="131408089200000000" Dst="0" />
<file name="cs.js" server="smoothgraph.co.th" local="131338806520000000" remote="131408089200000000" Dst="0" />
<file name="da.js" server="smoothgraph.co.th" local="131338806520000000" remote="131408089200000000" Dst="0" />
<file name="de.js" server="smoothgraph.co.th" local="131338806520000000" remote="131408089200000000" Dst="0" />
<file name="en_ca.js" server="smoothgraph.co.th" local="131338806520000000" remote="131408089200000000" Dst="0" />
<file name="en_gb.js" server="smoothgraph.co.th" local="131338806520000000" remote="131408089200000000" Dst="0" />
<file name="es.js" server="smoothgraph.co.th" local="131338806520000000" remote="131408089800000000" Dst="0" />
<file name="et.js" server="smoothgraph.co.th" local="131338806520000000" remote="131408089800000000" Dst="0" />
<file name="fa.js" server="smoothgraph.co.th" local="131338806520000000" remote="131408089800000000" Dst="0" />
<file name="fi.js" server="smoothgraph.co.th" local="131338806520000000" remote="131408089800000000" Dst="0" />
<file name="fr.js" server="smoothgraph.co.th" local="131338806520000000" remote="131408089800000000" Dst="0" />
<file name="he.js" server="smoothgraph.co.th" local="131338806520000000" remote="131408089800000000" Dst="0" />
<file name="hr.js" server="smoothgraph.co.th" local="131338806520000000" remote="131408089800000000" Dst="0" />
<file name="hu.js" server="smoothgraph.co.th" local="131338806520000000" remote="131408089800000000" Dst="0" />
<file name="id.js" server="smoothgraph.co.th" local="131338806520000000" remote="131408089800000000" Dst="0" />
<file name="it.js" server="smoothgraph.co.th" local="131338806520000000" remote="131408089800000000" Dst="0" />
<file name="ja.js" server="smoothgraph.co.th" local="131338806520000000" remote="131408089800000000" Dst="0" />
<file name="ko.js" server="smoothgraph.co.th" local="131338806520000000" remote="131408089800000000" Dst="0" />
<file name="me.js" server="smoothgraph.co.th" local="131338806520000000" remote="131408089800000000" Dst="0" />
<file name="nb.js" server="smoothgraph.co.th" local="131338806520000000" remote="131408089800000000" Dst="0" />
<file name="nl.js" server="smoothgraph.co.th" local="131338806520000000" remote="131408089800000000" Dst="0" />
<file name="pl.js" server="smoothgraph.co.th" local="131338806520000000" remote="131408089800000000" Dst="0" />
<file name="pt_br.js" server="smoothgraph.co.th" local="131338806520000000" remote="131408089800000000" Dst="0" />
<file name="pt_pt.js" server="smoothgraph.co.th" local="131338806520000000" remote="131408089800000000" Dst="0" />
<file name="ro.js" server="smoothgraph.co.th" local="131338806520000000" remote="131408089800000000" Dst="0" />
<file name="ru.js" server="smoothgraph.co.th" local="131338806520000000" remote="131408089800000000" Dst="0" />
<file name="sk.js" server="smoothgraph.co.th" local="131338806520000000" remote="131408089800000000" Dst="0" />
<file name="sr.js" server="smoothgraph.co.th" local="131338806520000000" remote="131408089800000000" Dst="0" />
<file name="sv.js" server="smoothgraph.co.th" local="131338806520000000" remote="131408089800000000" Dst="0" />
<file name="tr.js" server="smoothgraph.co.th" local="131338806520000000" remote="131408089800000000" Dst="0" />
<file name="th.js" server="smoothgraph.co.th" local="131338806520000000" remote="131408089800000000" Dst="0" />
<file name="ua.js" server="smoothgraph.co.th" local="131338806520000000" remote="131408089800000000" Dst="0" />
<file name="vi.js" server="smoothgraph.co.th" local="131338806520000000" remote="131408089800000000" Dst="0" />
<file name="zh_cn.js" server="smoothgraph.co.th" local="131338806520000000" remote="131408089800000000" Dst="0" />
<file name="zh_tw.js" server="smoothgraph.co.th" local="131338806520000000" remote="131408089800000000" Dst="0" />
</dwsync>